lv_namedays/__init__.py
lv_namedays/__main__.py
lv_namedays/cli.py
lv_namedays/nameday.py
lv_namedays/data/paplasinatais_saraksts.json
lv_namedays/data/tradic_vardadienu_saraksts.json
lv_namedays-0.6.dist-info/METADATA
lv_namedays-0.6.dist-info/WHEEL
lv_namedays-0.6.dist-info/entry_points.txt
lv_namedays-0.6.dist-info/licenses/LICENSE
lv_namedays-0.6.dist-info/RECORD
