Metadata-Version: 2.4
Name: lv-namedays
Version: 0.6
Summary: a CLI tool and a library for Latvian name day lookup
Project-URL: homepage, https://github.com/CaptSolo/lv-namedays
Project-URL: issues, https://github.com/CaptSolo/lv-namedays/issues
Author: CaptSolo
License-File: LICENSE
Keywords: CLI,Latvian,name days,nameday,vārda dienas
Classifier: License :: OSI Approved :: MIT License
Classifier: Operating System :: OS Independent
Classifier: Programming Language :: Python :: 3
Classifier: Programming Language :: Python :: 3.10
Classifier: Programming Language :: Python :: 3.11
Classifier: Programming Language :: Python :: 3.12
Classifier: Programming Language :: Python :: 3.13
Classifier: Programming Language :: Python :: 3.14
Requires-Python: >=3.10
Requires-Dist: click
Provides-Extra: convert
Requires-Dist: openpyxl; extra == 'convert'
Requires-Dist: pandas; extra == 'convert'
